mpl_histcolorbar/__init__.py
mpl_histcolorbar/_histcolorbar.py
mpl_histcolorbar-0.1.1.dist-info/LICENSE
mpl_histcolorbar-0.1.1.dist-info/METADATA
mpl_histcolorbar-0.1.1.dist-info/WHEEL
mpl_histcolorbar-0.1.1.dist-info/top_level.txt
mpl_histcolorbar-0.1.1.dist-info/RECORD
